ecofaber/__init__.py
ecofaber/basemodel.py
ecofaber/gui.py
ecofaber/rendering.py
ecofaber/utils.py
ecofaber/icons/close.png
ecofaber/icons/load.png
ecofaber/icons/next.png
ecofaber/icons/pause.png
ecofaber/icons/play.png
ecofaber/icons/reset.png
ecofaber/icons/save.png
ecofaber/icons/view.png
ecofaber-0.0.3.dist-info/LICENSE
ecofaber-0.0.3.dist-info/METADATA
ecofaber-0.0.3.dist-info/WHEEL
ecofaber-0.0.3.dist-info/top_level.txt
ecofaber-0.0.3.dist-info/RECORD
